daim/__init__.py
daim/annotate_identified_variants.py
naim/__init__.py
naim/annotate_identified_variants.py
naim-0.2.14.dist-info/LICENSE.txt
naim-0.2.14.dist-info/METADATA
naim-0.2.14.dist-info/WHEEL
naim-0.2.14.dist-info/top_level.txt
naim-0.2.14.dist-info/RECORD
