Metadata-Version: 2.1
Name: naim
Version: 0.2.14
Summary: A variant annotation package
Home-page: https://github.com/nesegunes
Author: tardis
Author-email: nesegunes.ce@gmail.com
License: UNKNOWN
Platform: UNKNOWN
Classifier: Programming Language :: Python :: 3
Classifier: License :: OSI Approved :: MIT License
Classifier: Operating System :: OS Independent
Requires-Python: >=3.6
Requires-Dist: myvariant
